s3ball/__init__.py
s3ball/cli.py
s3ball/download.py
s3ball/options.py
s3ball/upload.py
s3ball-0.1.1.dist-info/LICENSE
s3ball-0.1.1.dist-info/METADATA
s3ball-0.1.1.dist-info/WHEEL
s3ball-0.1.1.dist-info/entry_points.txt
s3ball-0.1.1.dist-info/top_level.txt
s3ball-0.1.1.dist-info/RECORD
